PVBM/CentralRetinalAnalysis.py
PVBM/Datasets.py
PVBM/DiscSegmenter.py
PVBM/FractalAnalysis.py
PVBM/GeometricalAnalysis.py
PVBM/GeometryAnalysis.py
PVBM/LesionSegmenter.py
PVBM/__init__.py
PVBM/debug.py
PVBM/GraphCRE/GraphCentralRetinalEquivalent.py
PVBM/GraphCRE/__init__.py
PVBM/GraphRegularisation/GraphRegularisation.py
PVBM/GraphRegularisation/__init__.py
PVBM/helpers/__init__.py
PVBM/helpers/branching2.py
PVBM/helpers/branching_angle.py
PVBM/helpers/perimeter.py
PVBM/helpers/tortuosity.py
pvbm-3.0.1.0.dist-info/licenses/LICENSE
pvbm-3.0.1.0.dist-info/METADATA
pvbm-3.0.1.0.dist-info/WHEEL
pvbm-3.0.1.0.dist-info/top_level.txt
pvbm-3.0.1.0.dist-info/RECORD
