Metadata-Version: 2.4
Name: pvbm
Version: 3.0.1.0
Summary: Python Vasculature Biomarker toolbox
Home-page: https://github.com/aim-lab/PVBM
Author: Jonathan Fhima, Yevgeniy Men
Author-email: jonathanfh@campus.technion.ac.il
License-File: LICENSE
Requires-Dist: numpy
Requires-Dist: scipy
Requires-Dist: scikit-image
Requires-Dist: pillow
Requires-Dist: gdown
Requires-Dist: onnxruntime
Requires-Dist: torchvision
Requires-Dist: opencv-python
Requires-Dist: matplotlib
Dynamic: author
Dynamic: author-email
Dynamic: description
Dynamic: description-content-type
Dynamic: home-page
Dynamic: license-file
Dynamic: requires-dist
Dynamic: summary
